invenio_records_rest/__init__.py
invenio_records_rest/_compat.py
invenio_records_rest/config.py
invenio_records_rest/errors.py
invenio_records_rest/ext.py
invenio_records_rest/facets.py
invenio_records_rest/links.py
invenio_records_rest/proxies.py
invenio_records_rest/query.py
invenio_records_rest/sorter.py
invenio_records_rest/utils.py
invenio_records_rest/views.py
invenio_records_rest/loaders/__init__.py
invenio_records_rest/loaders/marshmallow.py
invenio_records_rest/schemas/__init__.py
invenio_records_rest/schemas/json.py
invenio_records_rest/schemas/fields/__init__.py
invenio_records_rest/schemas/fields/datetime.py
invenio_records_rest/schemas/fields/generated.py
invenio_records_rest/schemas/fields/marshmallow_contrib.py
invenio_records_rest/schemas/fields/persistentidentifier.py
invenio_records_rest/schemas/fields/sanitizedhtml.py
invenio_records_rest/schemas/fields/sanitizedunicode.py
invenio_records_rest/schemas/fields/trimmedstring.py
invenio_records_rest/serializers/__init__.py
invenio_records_rest/serializers/base.py
invenio_records_rest/serializers/citeproc.py
invenio_records_rest/serializers/csv.py
invenio_records_rest/serializers/datacite.py
invenio_records_rest/serializers/dc.py
invenio_records_rest/serializers/json.py
invenio_records_rest/serializers/jsonld.py
invenio_records_rest/serializers/marshmallow.py
invenio_records_rest/serializers/response.py
invenio_records_rest/translations/messages.pot
invenio_records_rest/translations/ar/LC_MESSAGES/messages.mo
invenio_records_rest/translations/ar/LC_MESSAGES/messages.po
invenio_records_rest/translations/bg/LC_MESSAGES/messages.mo
invenio_records_rest/translations/bg/LC_MESSAGES/messages.po
invenio_records_rest/translations/ca/LC_MESSAGES/messages.mo
invenio_records_rest/translations/ca/LC_MESSAGES/messages.po
invenio_records_rest/translations/cs/LC_MESSAGES/messages.mo
invenio_records_rest/translations/cs/LC_MESSAGES/messages.po
invenio_records_rest/translations/da/LC_MESSAGES/messages.mo
invenio_records_rest-3.2.1.dist-info/licenses/AUTHORS.rst
invenio_records_rest-3.2.1.dist-info/licenses/LICENSE
invenio_records_rest-3.2.1.dist-info/METADATA
invenio_records_rest-3.2.1.dist-info/WHEEL
invenio_records_rest-3.2.1.dist-info/entry_points.txt
invenio_records_rest-3.2.1.dist-info/top_level.txt
invenio_records_rest-3.2.1.dist-info/RECORD
