Metadata-Version: 2.4
Name: invenio-records-rest
Version: 3.2.1
Summary: "REST API for invenio-records."
Home-page: https://github.com/inveniosoftware/invenio-records-rest
Author: CERN
Author-email: info@inveniosoftware.org
License: MIT
Keywords: invenio api
Platform: any
Classifier: Development Status :: 5 - Production/Stable
Requires-Python: >=3.7
License-File: LICENSE
License-File: AUTHORS.rst
Requires-Dist: bleach>=2.1.3
Requires-Dist: ftfy>=4.4.3
Requires-Dist: invenio-base<3.0.0,>=2.0.0
Requires-Dist: invenio-pidstore<3.0.0,>=2.0.0
Requires-Dist: invenio-records<4.0.0,>=3.0.0
Requires-Dist: invenio-rest<3.0.0,>=2.0.0
Requires-Dist: invenio-indexer<4.0.0,>=3.0.0
Requires-Dist: invenio-i18n<4.0.0,>=3.0.0
Provides-Extra: tests
Requires-Dist: cryptography>=2.1.4; extra == "tests"
Requires-Dist: pytest-black-ng>=0.4.0; extra == "tests"
Requires-Dist: Flask-Login>=0.3.2; extra == "tests"
Requires-Dist: invenio-config<2.0.0,>=1.0.2; extra == "tests"
Requires-Dist: invenio-db[mysql,postgresql]<3.0.0,>=2.0.0; extra == "tests"
Requires-Dist: pytest-invenio<4.0.0,>=3.0.0; extra == "tests"
Requires-Dist: citeproc-py>=0.6.0; extra == "tests"
Requires-Dist: citeproc-py-styles>=0.1.3; extra == "tests"
Requires-Dist: datacite>=1.0.1; extra == "tests"
Requires-Dist: sphinx>=4.5; extra == "tests"
Requires-Dist: dcxml>=0.1.2; extra == "tests"
Requires-Dist: pyld<2,>=1.0.5; extra == "tests"
Requires-Dist: mock>=4; extra == "tests"
Provides-Extra: elasticsearch7
Requires-Dist: invenio-search[elasticsearch7]<4.0.0,>=3.0.0; extra == "elasticsearch7"
Provides-Extra: opensearch1
Requires-Dist: invenio-search[opensearch1]<4.0.0,>=3.0.0; extra == "opensearch1"
Provides-Extra: opensearch2
Requires-Dist: invenio-search[opensearch2]<4.0.0,>=3.0.0; extra == "opensearch2"
Provides-Extra: citeproc
Requires-Dist: citeproc-py>=0.6.0; extra == "citeproc"
Requires-Dist: citeproc-py-styles>=0.1.3; extra == "citeproc"
Provides-Extra: datacite
Requires-Dist: datacite>=1.0.1; extra == "datacite"
Provides-Extra: docs
Provides-Extra: dublincore
Requires-Dist: dcxml>=0.1.2; extra == "dublincore"
Provides-Extra: jsonld
Requires-Dist: pyld<2,>=1.0.5; extra == "jsonld"
Dynamic: license-file
